{
	"id": "hmu2000",
	"name": "hmu2000",
	"type": "HMUElement",
	"version": "1.0.0",
	"description": "test",
	"path": "/usr/bin/aggregation/element-lib/hmu2000.json",
	"channels": [
		{
			"id": "id",
			"name": "HMUID",
			"datatype": "string",
			"value": null
		},
		{
			"id": "netmode",
			"name": "网络模式",
			"datatype": "string",
			"value": null
		},
		{
			"id": "longitude",
			"name": "经度",
			"datatype": "string",
			"value": null
		},
		{
			"id": "latitude",
			"name": "纬度",
			"datatype": "string",
			"value": null
		},
		{
			"id": "utctime",
			"name": "UTC时间",
			"datatype": "string",
			"value": null
		},
		{
			"id": "uptime",
			"name": "系统启动时间",
			"datatype": "string",
			"value": null
		},
		{
			"id": "currtime",
			"name": "当前系统时间",
			"datatype": "string",
			"value": null
		},
		{
			"id": "timeserver",
			"name": "对时服务器",
			"datatype": "string",
			"value": null
		},
		{
			"id": "cpu",
			"name": "CPU型号",
			"datatype": "string",
			"value": null
		},
		{
			"id": "model",
			"name": "机型",
			"datatype": "string",
			"value": null
		},
		{
			"id": "swversion",
			"name": "软件版本",
			"datatype": "string",
			"value": null
		},
		{
			"id": "hwversion",
			"name": "硬件版本",
			"datatype": "string",
			"value": null
		},
		{
			"id": "ramtotal",
			"name": "RAM总数",
			"datatype": "string",
			"value": null
		},
		{
			"id": "ramfree",
			"name": "剩余RAM",
			"datatype": "string",
			"value": null
		},
		{
			"id": "flashtotal",
			"name": "FLASH总大小",
			"datatype": "string",
			"value": null
		},
		{
			"id": "flashfree",
			"name": "FLASH剩余空间",
			"datatype": "string",
			"value": null
		},
		{
			"id": "sdtotal",
			"name": "TF卡总大小",
			"datatype": "string",
			"value": null
		},
		{
			"id": "sdfree",
			"name": "TF卡剩余",
			"datatype": "string",
			"value": null
		},
		{
			"id": "kernelver",
			"name": "内核版本",
			"datatype": "string",
			"value": null
		},
		{
			"id": "pciedev",
			"name": "PCIE设备",
			"datatype": "string",
			"value": null
		},
		{
			"id": "lanip",
			"name": "网关IP",
			"datatype": "string",
			"value": null
		},
		{
			"id": "lanmask",
			"name": "子网掩码",
			"datatype": "string",
			"value": null
		},
		{
			"id": "lanmac",
			"name": "lan硬件地址",
			"datatype": "string",
			"value": null
		},
		{
			"id": "wanip",
			"name": "有线联网ip",
			"datatype": "string",
			"value": null
		},
		{
			"id": "wanmask",
			"name": "有线联网掩码",
			"datatype": "string",
			"value": null
		},
		{
			"id": "wangateway",
			"name": "有线联网网关",
			"datatype": "string",
			"value": null
		},
		{
			"id": "wanmac",
			"name": "有线联网硬件地址",
			"datatype": "string",
			"value": null
		},
		{
			"id": "wanpdns",
			"name": "有线联网首选dns",
			"datatype": "string",
			"value": null
		},
		{
			"id": "wansdns",
			"name": "有线联网备用dns",
			"datatype": "string",
			"value": null
		},
		{
			"id": "wifissid",
			"name": "ssid",
			"datatype": "string",
			"value": null
		},
		{
			"id": "wifipass",
			"name": "密码",
			"datatype": "string",
			"value": null
		}
	],
	"mappings": [
		{
			"protocol": "protocol-hyiot-mu",
			"type": "HMUProtocol",
			"setting": {
				"throttle": 0,
				"optimized": false,
				"stepDiff": 0,
				"maxDiff": 0,
				"cov": 0
			},
			"mapping": [
				{
					"code": 0,
					"address": 0,
					"quantity": 0,
					"format": "",
					"expression": "",
					"channel": "id"
				},
				{
					"code": 0,
					"address": 0,
					"quantity": 0,
					"format": "",
					"expression": "",
					"channel": "netmode"
				},
				{
					"code": 0,
					"address": 0,
					"quantity": 0,
					"format": "",
					"expression": "",
					"channel": "longitude"
				},
				{
					"code": 0,
					"address": 0,
					"quantity": 0,
					"format": "",
					"expression": "",
					"channel": "latitude"
				},
				{
					"code": 0,
					"address": 0,
					"quantity": 0,
					"format": "",
					"expression": "",
					"channel": "utctime"
				},
				{
					"code": 0,
					"address": 0,
					"quantity": 0,
					"format": "",
					"expression": "",
					"channel": "uptime"
				},
				{
					"code": 0,
					"address": 0,
					"quantity": 0,
					"format": "",
					"expression": "",
					"channel": "currtime"
				},
				{
					"code": 0,
					"address": 0,
					"quantity": 0,
					"format": "",
					"expression": "",
					"channel": "timeserver"
				},
				{
					"code": 0,
					"address": 0,
					"quantity": 0,
					"format": "",
					"expression": "",
					"channel": "cpu"
				},
				{
					"code": 0,
					"address": 0,
					"quantity": 0,
					"format": "",
					"expression": "",
					"channel": "model"
				},
				{
					"code": 0,
					"address": 0,
					"quantity": 0,
					"format": "",
					"expression": "",
					"channel": "swversion"
				},
				{
					"code": 0,
					"address": 0,
					"quantity": 0,
					"format": "",
					"expression": "",
					"channel": "hwversion"
				},
				{
					"code": 0,
					"address": 0,
					"quantity": 0,
					"format": "",
					"expression": "",
					"channel": "ramtotal"
				},
				{
					"code": 0,
					"address": 0,
					"quantity": 0,
					"format": "",
					"expression": "",
					"channel": "ramfree"
				},
				{
					"code": 0,
					"address": 0,
					"quantity": 0,
					"format": "",
					"expression": "",
					"channel": "flashtotal"
				},
				{
					"code": 0,
					"address": 0,
					"quantity": 0,
					"format": "",
					"expression": "",
					"channel": "flashfree"
				},
				{
					"code": 0,
					"address": 0,
					"quantity": 0,
					"format": "",
					"expression": "",
					"channel": "sdtotal"
				},
				{
					"code": 0,
					"address": 0,
					"quantity": 0,
					"format": "",
					"expression": "",
					"channel": "sdfree"
				},
				{
					"code": 0,
					"address": 0,
					"quantity": 0,
					"format": "",
					"expression": "",
					"channel": "kernelver"
				},
				{
					"code": 0,
					"address": 0,
					"quantity": 0,
					"format": "",
					"expression": "",
					"channel": "pciedev"
				},
				{
					"code": 0,
					"address": 0,
					"quantity": 0,
					"format": "",
					"expression": "",
					"channel": "lanip"
				},
				{
					"code": 0,
					"address": 0,
					"quantity": 0,
					"format": "",
					"expression": "",
					"channel": "lanmask"
				},
				{
					"code": 0,
					"address": 0,
					"quantity": 0,
					"format": "",
					"expression": "",
					"channel": "lanmac"
				},
				{
					"code": 0,
					"address": 0,
					"quantity": 0,
					"format": "",
					"expression": "",
					"channel": "wanip"
				},
				{
					"code": 0,
					"address": 0,
					"quantity": 0,
					"format": "",
					"expression": "",
					"channel": "wanmask"
				},
				{
					"code": 0,
					"address": 0,
					"quantity": 0,
					"format": "",
					"expression": "",
					"channel": "wangateway"
				},
				{
					"code": 0,
					"address": 0,
					"quantity": 0,
					"format": "",
					"expression": "",
					"channel": "wanmac"
				},
				{
					"code": 0,
					"address": 0,
					"quantity": 0,
					"format": "",
					"expression": "",
					"channel": "wanpdns"
				},
				{
					"code": 0,
					"address": 0,
					"quantity": 0,
					"format": "",
					"expression": "",
					"channel": "wansdns"
				},
				{
					"code": 0,
					"address": 0,
					"quantity": 0,
					"format": "",
					"expression": "",
					"channel": "wifissid"
				},
				{
					"code": 0,
					"address": 0,
					"quantity": 0,
					"format": "",
					"expression": "",
					"channel": "wifipass"
				}
			]
		}
	]
}